<?xml version="1.0" ?>
<tv generator-info-name="TeleRed Playwright GitHub XMLTV" generator-info-url="https://www.telered.com.ar">
  <channel id="canal.7">
    <display-name>7 - Canal Provincial 7 Ver</display-name>
  </channel>
  <channel id="canal.8">
    <display-name>8 - Net TV 8 Ver</display-name>
  </channel>
  <channel id="canal.10">
    <display-name>10 - TELEFE 10 Ver</display-name>
  </channel>
  <channel id="canal.11">
    <display-name>11 - TV</display-name>
  </channel>
  <channel id="canal.12">
    <display-name>12 - El Trece 12 Ver</display-name>
  </channel>
  <channel id="canal.13">
    <display-name>13 - El Nueve 13 Ver</display-name>
  </channel>
  <channel id="canal.14">
    <display-name>14 - Encuentro 14 Ver</display-name>
  </channel>
  <channel id="canal.15">
    <display-name>15 - TN 15 Ver</display-name>
  </channel>
  <channel id="canal.16">
    <display-name>16 - A24 16 Ver</display-name>
  </channel>
  <channel id="canal.17">
    <display-name>17 - C5N 17 Ver</display-name>
  </channel>
  <channel id="canal.19">
    <display-name>19 - Canal 26 19 Ver</display-name>
  </channel>
  <channel id="canal.20">
    <display-name>20 - LN+ 20 Ver</display-name>
  </channel>
  <channel id="canal.21">
    <display-name>21 - IP 21 Ver</display-name>
  </channel>
  <channel id="canal.24">
    <display-name>24 - Orbe 21 24 Ver</display-name>
  </channel>
  <channel id="canal.25">
    <display-name>25 - CONSTRUIR 25 Ver</display-name>
  </channel>
  <channel id="canal.45">
    <display-name>45 - TeleRed 45 Ver</display-name>
  </channel>
  <programme start="20260721040000 -0300" stop="20260721080000 -0300" channel="canal.45">
    <title lang="es">Local SM</title>
  </programme>
  <programme start="20260721080000 -0300" stop="20260721100000 -0300" channel="canal.45">
    <title lang="es">Local SM</title>
  </programme>
  <channel id="canal.50">
    <display-name>50 - TyC Sports 50 Ver</display-name>
  </channel>
  <channel id="canal.51">
    <display-name>51 - ESPN 51 Ver</display-name>
  </channel>
  <channel id="canal.52">
    <display-name>52 - ESPN 2 52 Ver</display-name>
  </channel>
  <channel id="canal.53">
    <display-name>53 - ESPN 3 53 Ver</display-name>
  </channel>
  <channel id="canal.54">
    <display-name>54 - FOX Sports 54 Ver</display-name>
  </channel>
  <channel id="canal.55">
    <display-name>55 - FOX Sports 2 55 Ver</display-name>
  </channel>
  <programme start="20260721030000 -0300" stop="20260721070000 -0300" channel="canal.55">
    <title lang="es">Fox Sports 2</title>
  </programme>
  <programme start="20260721070000 -0300" stop="20260721090000 -0300" channel="canal.55">
    <title lang="es">Fox Sports 2</title>
  </programme>
  <channel id="canal.56">
    <display-name>56 - FOX Sports 3 56 Ver</display-name>
  </channel>
  <programme start="20260721040000 -0300" stop="20260721060000 -0300" channel="canal.56">
    <title lang="es">Fox Sports 3</title>
  </programme>
  <channel id="canal.58">
    <display-name>58 - ESPN Premium 58 Ver</display-name>
  </channel>
  <channel id="canal.59">
    <display-name>59 - TNT Sport Premium 59 Ver</display-name>
  </channel>
  <channel id="canal.60">
    <display-name>60 - DEPORTV 60 Ver</display-name>
  </channel>
  <channel id="canal.62">
    <display-name>62 - Golf Channel 62 Ver</display-name>
  </channel>
  <channel id="canal.63">
    <display-name>63 - TURBO 63 Ver</display-name>
  </channel>
  <channel id="canal.64">
    <display-name>64 - El Garage 64 Ver</display-name>
  </channel>
  <channel id="canal.108">
    <display-name>108 - Net TV 108 Ver</display-name>
  </channel>
  <channel id="canal.110">
    <display-name>110 - AMERICA HD 110 Ver</display-name>
  </channel>
  <channel id="canal.111">
    <display-name>111 - TV</display-name>
  </channel>
  <channel id="canal.112">
    <display-name>112 - El Nueve HD 112 Ver</display-name>
  </channel>
  <channel id="canal.113">
    <display-name>113 - TELEFE HD 113 Ver</display-name>
  </channel>
  <channel id="canal.114">
    <display-name>114 - El Trece HD 114 Ver</display-name>
  </channel>
  <channel id="canal.115">
    <display-name>115 - TN HD 115 Ver</display-name>
  </channel>
  <channel id="canal.116">
    <display-name>116 - C5N HD 116 Ver</display-name>
  </channel>
  <channel id="canal.117">
    <display-name>117 - A24 HD 117 Ver</display-name>
  </channel>
  <channel id="canal.118">
    <display-name>118 - LN+ 118 Ver</display-name>
  </channel>
  <channel id="canal.119">
    <display-name>119 - IP HD 119 Ver</display-name>
  </channel>
  <channel id="canal.120">
    <display-name>120 - TYC SPORTS HD 120 Ver</display-name>
  </channel>
  <channel id="canal.121">
    <display-name>121 - ESPN HD 121 Ver</display-name>
  </channel>
  <channel id="canal.122">
    <display-name>122 - ESPN 2 HD 122 Ver</display-name>
  </channel>
  <channel id="canal.123">
    <display-name>123 - ESPN 3 HD 123 Ver</display-name>
  </channel>
  <channel id="canal.124">
    <display-name>124 - ESPN EXTRA HD 124 Ver</display-name>
  </channel>
  <channel id="canal.125">
    <display-name>125 - FOX SPORTS HD 125 Ver</display-name>
  </channel>
  <channel id="canal.126">
    <display-name>126 - FOX SPORTS 2 HD 126 Ver</display-name>
  </channel>
  <programme start="20260721030000 -0300" stop="20260721070000 -0300" channel="canal.126">
    <title lang="es">Fox Sports 2</title>
  </programme>
  <programme start="20260721070000 -0300" stop="20260721090000 -0300" channel="canal.126">
    <title lang="es">Fox Sports 2</title>
  </programme>
  <channel id="canal.127">
    <display-name>127 - FOX Sports 3 HD 127 Ver</display-name>
  </channel>
  <programme start="20260721040000 -0300" stop="20260721060000 -0300" channel="canal.127">
    <title lang="es">Fox Sports 3</title>
  </programme>
  <channel id="canal.128">
    <display-name>128 - ESPN Premium HD 128 Ver</display-name>
  </channel>
  <channel id="canal.129">
    <display-name>129 - TNT Sport Premium HD 129 Ver</display-name>
  </channel>
  <channel id="canal.131">
    <display-name>131 - DEPORTV HD 131 Ver</display-name>
  </channel>
  <channel id="canal.132">
    <display-name>132 - Golf Channel HD 132 Ver</display-name>
  </channel>
  <channel id="canal.133">
    <display-name>133 - TURBO HD 133 Ver</display-name>
  </channel>
  <channel id="canal.150">
    <display-name>150 - HBO HD 150 Ver</display-name>
  </channel>
  <channel id="canal.151">
    <display-name>151 - HBO POP HD 151 Ver</display-name>
  </channel>
  <channel id="canal.152">
    <display-name>152 - HBO XTREME HD 152 Ver</display-name>
  </channel>
  <channel id="canal.153">
    <display-name>153 - HBO family HD 153 Ver</display-name>
  </channel>
  <channel id="canal.154">
    <display-name>154 - HBO MUNDI HD 154 Ver</display-name>
  </channel>
  <channel id="canal.155">
    <display-name>155 - HBO 2 HD 155 Ver</display-name>
  </channel>
  <channel id="canal.156">
    <display-name>156 - HBO plus HD 156 Ver</display-name>
  </channel>
  <channel id="canal.157">
    <display-name>157 - HBO Signature HD 157 Ver</display-name>
  </channel>
  <channel id="canal.158">
    <display-name>158 - SONY MOVIES HD 158 Ver</display-name>
  </channel>
  <channel id="canal.159">
    <display-name>159 - Cinemax HD 159 Ver</display-name>
  </channel>
  <channel id="canal.160">
    <display-name>160 - CINECANAL HD 160 Ver</display-name>
  </channel>
  <channel id="canal.161">
    <display-name>161 - SPACE HD 161 Ver</display-name>
  </channel>
  <channel id="canal.162">
    <display-name>162 - TNT HD 162 Ver</display-name>
  </channel>
  <channel id="canal.163">
    <display-name>163 - SONY HD 163 Ver</display-name>
  </channel>
  <channel id="canal.166">
    <display-name>166 - Warner HD 166 Ver</display-name>
  </channel>
  <channel id="canal.167">
    <display-name>167 - AXN HD 167 Ver</display-name>
  </channel>
  <channel id="canal.168">
    <display-name>168 - FX HD 168 Ver</display-name>
  </channel>
  <channel id="canal.169">
    <display-name>169 - GOLDEN HD 169 Ver</display-name>
  </channel>
  <channel id="canal.170">
    <display-name>170 - STAR CHANNEL HD 170 Ver</display-name>
  </channel>
  <channel id="canal.171">
    <display-name>171 - AMC HD 171 Ver</display-name>
  </channel>
  <channel id="canal.172">
    <display-name>172 - LIFETIME HD 172 Ver</display-name>
  </channel>
  <channel id="canal.173">
    <display-name>173 - TNT Series HD 173 Ver</display-name>
  </channel>
  <channel id="canal.174">
    <display-name>174 - Discovery Science HD 174 Ver</display-name>
  </channel>
  <channel id="canal.175">
    <display-name>175 - TLC HD 175 Ver</display-name>
  </channel>
  <channel id="canal.176">
    <display-name>176 - Comedy Central HD 176 Ver</display-name>
  </channel>
  <channel id="canal.177">
    <display-name>177 - adult swim 177 Ver</display-name>
  </channel>
  <channel id="canal.178">
    <display-name>178 - SUN Channel HD 178 Ver</display-name>
  </channel>
  <channel id="canal.179">
    <display-name>179 - Discovery Channel HD 179 Ver</display-name>
  </channel>
  <channel id="canal.180">
    <display-name>180 - NATIONAL GEOGRAPHIC HD 180 Ver</display-name>
  </channel>
  <channel id="canal.181">
    <display-name>181 - Animal Planet HD 181 Ver</display-name>
  </channel>
  <channel id="canal.182">
    <display-name>182 - History Channel HD 182 Ver</display-name>
  </channel>
  <channel id="canal.183">
    <display-name>183 - Discovery Theater HD 183 Ver</display-name>
  </channel>
  <channel id="canal.184">
    <display-name>184 - Discovery World HD 184 Ver</display-name>
  </channel>
  <channel id="canal.185">
    <display-name>185 - FOOD NETWORK HD 185 Ver</display-name>
  </channel>
  <channel id="canal.186">
    <display-name>186 - el Gourmet HD 186 Ver</display-name>
  </channel>
  <channel id="canal.188">
    <display-name>188 - ESTRELLAS HD 188 Ver</display-name>
  </channel>
  <channel id="canal.189">
    <display-name>189 - Rai HD 189 Ver</display-name>
  </channel>
  <channel id="canal.191">
    <display-name>191 - TELEHIT HD 191 Ver</display-name>
  </channel>
  <channel id="canal.192">
    <display-name>192 - CM HD 192 Ver</display-name>
  </channel>
  <channel id="canal.193">
    <display-name>193 - Nickelodeon HD 193 Ver</display-name>
  </channel>
  <channel id="canal.194">
    <display-name>194 - Nick Jr HD 194 Ver</display-name>
  </channel>
  <channel id="canal.195">
    <display-name>195 - Disney channel HD 195 Ver</display-name>
  </channel>
  <channel id="canal.196">
    <display-name>196 - CARTOON NETWORK HD 196 Ver</display-name>
  </channel>
  <channel id="canal.197">
    <display-name>197 - Discovery Kids HD 197 Ver</display-name>
  </channel>
  <channel id="canal.198">
    <display-name>198 - Disney Junior HD 198 Ver</display-name>
  </channel>
  <channel id="canal.200">
    <display-name>200 - AXN 200 Ver</display-name>
  </channel>
  <channel id="canal.201">
    <display-name>201 - Cinecanal 201 Ver</display-name>
  </channel>
  <channel id="canal.202">
    <display-name>202 - EUROCHANNEL 202 Ver</display-name>
  </channel>
  <channel id="canal.203">
    <display-name>203 - Europa Europa 203 Ver</display-name>
  </channel>
  <channel id="canal.204">
    <display-name>204 - Cinemax 204 Ver</display-name>
  </channel>
  <channel id="canal.205">
    <display-name>205 - STAR CHANNEL 205 Ver</display-name>
  </channel>
  <channel id="canal.208">
    <display-name>208 - SONY 208 Ver</display-name>
  </channel>
  <channel id="canal.209">
    <display-name>209 - SPACE 209 Ver</display-name>
  </channel>
  <channel id="canal.210">
    <display-name>210 - SONY MOVIES 210 Ver</display-name>
  </channel>
  <channel id="canal.211">
    <display-name>211 - TNT 211 Ver</display-name>
  </channel>
  <channel id="canal.212">
    <display-name>212 - TNT Series 212 Ver</display-name>
  </channel>
  <channel id="canal.213">
    <display-name>213 - VOLVER 213 Ver</display-name>
  </channel>
  <channel id="canal.214">
    <display-name>214 - Warner 214 Ver</display-name>
  </channel>
  <channel id="canal.215">
    <display-name>215 - AMC 215 Ver</display-name>
  </channel>
  <channel id="canal.216">
    <display-name>216 - TCM 216 Ver</display-name>
  </channel>
  <channel id="canal.217">
    <display-name>217 - FX 217 Ver</display-name>
  </channel>
  <channel id="canal.218">
    <display-name>218 - LIFETIME 218 Ver</display-name>
  </channel>
  <channel id="canal.219">
    <display-name>219 - CINE.AR 219 Ver</display-name>
  </channel>
  <channel id="canal.220">
    <display-name>220 - Fi</display-name>
  </channel>
  <channel id="canal.222">
    <display-name>222 - Comedy Central 222 Ver</display-name>
  </channel>
  <channel id="canal.223">
    <display-name>223 - tnt novelas 223 Ver</display-name>
  </channel>
  <channel id="canal.250">
    <display-name>250 - HBO 250 Ver</display-name>
  </channel>
  <channel id="canal.251">
    <display-name>251 - HBO plus 251 Ver</display-name>
  </channel>
  <channel id="canal.252">
    <display-name>252 - HBO 2 252 Ver</display-name>
  </channel>
  <channel id="canal.253">
    <display-name>253 - HBO family 253 Ver</display-name>
  </channel>
  <channel id="canal.254">
    <display-name>254 - HBO MUNDI 254 Ver</display-name>
  </channel>
  <channel id="canal.255">
    <display-name>255 - HBO POP 255 Ver</display-name>
  </channel>
  <channel id="canal.256">
    <display-name>256 - HBO XTREME 256 Ver</display-name>
  </channel>
  <channel id="canal.257">
    <display-name>257 - HBO Signature 257 Ver</display-name>
  </channel>
  <channel id="canal.300">
    <display-name>300 - PAKA PAKA 300 Ver</display-name>
  </channel>
  <channel id="canal.301">
    <display-name>301 - CARTOONITO 301 Ver</display-name>
  </channel>
  <channel id="canal.302">
    <display-name>302 - CARTOON NETWORK 302 Ver</display-name>
  </channel>
  <channel id="canal.303">
    <display-name>303 - Discovery Kids 303 Ver</display-name>
  </channel>
  <channel id="canal.304">
    <display-name>304 - Disney Channel 304 Ver</display-name>
  </channel>
  <channel id="canal.307">
    <display-name>307 - Baby TV 307 Ver</display-name>
  </channel>
  <channel id="canal.308">
    <display-name>308 - Disney Junior 308 Ver</display-name>
  </channel>
  <channel id="canal.309">
    <display-name>309 - TOONCAST 309 Ver</display-name>
  </channel>
  <channel id="canal.310">
    <display-name>310 - Nickelodeon 310 Ver</display-name>
  </channel>
  <channel id="canal.311">
    <display-name>311 - Nick Jr 311 Ver</display-name>
  </channel>
  <channel id="canal.401">
    <display-name>401 - RURAL 401 Ver</display-name>
  </channel>
  <channel id="canal.402">
    <display-name>402 - ID 402 Ver</display-name>
  </channel>
  <channel id="canal.403">
    <display-name>403 - FOOD NETWORK 403 Ver</display-name>
  </channel>
  <channel id="canal.404">
    <display-name>404 - el Gourmet 404 Ver</display-name>
  </channel>
  <channel id="canal.408">
    <display-name>408 - Diputados 408 Ver</display-name>
  </channel>
  <channel id="canal.409">
    <display-name>409 - MAS CHIC 409 Ver</display-name>
  </channel>
  <channel id="canal.410">
    <display-name>410 - EWTN 410 Ver</display-name>
  </channel>
  <channel id="canal.412">
    <display-name>412 - CANAL A 412 Ver</display-name>
  </channel>
  <channel id="canal.413">
    <display-name>413 - METRO 413 Ver</display-name>
  </channel>
  <channel id="canal.414">
    <display-name>414 - Magazine 414 Ver</display-name>
  </channel>
  <channel id="canal.451">
    <display-name>451 - Animal Planet 451 Ver</display-name>
  </channel>
  <channel id="canal.452">
    <display-name>452 - Discovery Channel 452 Ver</display-name>
  </channel>
  <channel id="canal.453">
    <display-name>453 - Ho</display-name>
  </channel>
  <channel id="canal.454">
    <display-name>454 - History Channel 454 Ver</display-name>
  </channel>
  <channel id="canal.456">
    <display-name>456 - NATIONAL GEOGRAPHIC 456 Ver</display-name>
  </channel>
  <channel id="canal.457">
    <display-name>457 - TLC 457 Ver</display-name>
  </channel>
  <channel id="canal.458">
    <display-name>458 - HGTV 458 Ver</display-name>
  </channel>
  <channel id="canal.459">
    <display-name>459 - Discovery Science 459 Ver</display-name>
  </channel>
  <channel id="canal.461">
    <display-name>461 - HISTORY 2 461 Ver</display-name>
  </channel>
  <channel id="canal.462">
    <display-name>462 - SUN Channel 462 Ver</display-name>
  </channel>
  <channel id="canal.501">
    <display-name>501 - MTV 501 Ver</display-name>
  </channel>
  <channel id="canal.508">
    <display-name>508 - hTV 508 Ver</display-name>
  </channel>
  <programme start="20260721050000 -0300" stop="20260721070000 -0300" channel="canal.508">
    <title lang="es">HTV</title>
  </programme>
  <channel id="canal.509">
    <display-name>509 - CM 509 Ver</display-name>
  </channel>
  <channel id="canal.510">
    <display-name>510 - QUIERO 510 Ver</display-name>
  </channel>
  <channel id="canal.600">
    <display-name>600 - Telesur 600 Ver</display-name>
  </channel>
  <channel id="canal.601">
    <display-name>601 - ESTRELLAS 601 Ver</display-name>
  </channel>
  <channel id="canal.602">
    <display-name>602 - TV5MONDE 602 Ver</display-name>
  </channel>
  <channel id="canal.604">
    <display-name>604 - Rai 604 Ver</display-name>
  </channel>
  <channel id="canal.607">
    <display-name>607 - Canal Vasco 607 Ver</display-name>
  </channel>
  <channel id="canal.608">
    <display-name>608 - CNN internacional 608 Ver</display-name>
  </channel>
  <channel id="canal.609">
    <display-name>609 - CNN 609 Ver</display-name>
  </channel>
  <channel id="canal.611">
    <display-name>611 - FOX news 611 Ver</display-name>
  </channel>
  <channel id="canal.615">
    <display-name>615 - RTP 615 Ver</display-name>
  </channel>
  <channel id="canal.616">
    <display-name>616 - TV CHILE 616 Ver</display-name>
  </channel>
  <channel id="canal.618">
    <display-name>618 - Paraguay TV 618 Ver</display-name>
  </channel>
</tv>
